[
  {
    "name": "Cat Nap",
    "worldlength": 1600,
    "catstart": {
      "x": 7600,
      "y": 200
    },
    "stages": [
      {
        "name": "start",
        "number": 0,
        "backgroundImage": "start_background",
        "zones": [
          {
            "key": "first_exit",
            "shape": "rectangle",
            "x1": 800,
            "x2": 900,
            "y1": 0,
            "y2": 600,
            "enabled": false,
            "from": 1,
            "to": 0
          }
        ],
        "elements": [
          {
            "x": 400,
            "y": 590,
            "key": "start_sprite_floor"
          }
        ],
        "treats": [
          {
            "x": 1050,
            "y": 300,
            "key": "first_treat",
            "enable_zone": "first_exit"
          }
        ],
        "toys": [
          {
            "type": "ball",
            "x": 400,
            "y": 300
          }
        ]
      },
      {
        "name": "box",
        "number": 1,
        "backgroundImage": "box_background",
        "foregroundElements": [
          {
            "x": 272,
            "y": 139,
            "key": "box_foreground_box"
          }
        ],
        "elements": [
          {
            "x": 400,
            "y": 370,
            "key": "box_sprite_box_and_ground"
          }
        ],
        "zones": [
          {
            "key": "box_foreground_box",
            "shape": "rectangle",
            "enabled": true,
            "x1": 272,
            "x2": 528,
            "y1": 139,
            "y2": 580,
            "from": -1,
            "to": -1
          }
        ]
      },
      {
        "name": "post",
        "number": 2,
        "backgroundImage": "post_background",
        "foregroundElements": [],
        "elements": [
          {
            "x": 400,
            "y": 342,
            "key": "post_sprites"
          }
        ],
        "zones": []
      },
      {
        "name": "vase",
        "number": 3,
        "backgroundImage": "vase_background",
        "foregroundElements": [
          {
            "x": 268,
            "y": 201,
            "key": "vase_foreground"
          }
        ],
        "elements": [
          {
            "x": 400,
            "y": 410,
            "key": "vase_sprites"
          }
        ],
        "zones": [
          {
            "key": "vase_foreground",
            "shape": "circle",
            "radius": 130,
            "enabled": true,
            "x": 400,
            "y": 420,
            "from": -1,
            "to": -1
          }
        ]
      },
      {
        "name": "boot",
        "number": 4,
        "backgroundImage": "boot_background",
        "foregroundElements": [
          {
            "x": 210,
            "y": 277,
            "key": "boot_foreground"
          }
        ],
        "elements": [
          {
            "x": 400,
            "y": 439,
            "key": "boot_sprites"
          }
        ],
        "zones": [
          {
            "key": "boot_foreground",
            "shape": "circle",
            "radius": 125,
            "enabled": true,
            "x": 360,
            "y": 480,
            "from": -1,
            "to": -1
          }
        ]
      },
      {
        "name": "bar",
        "number": 5,
        "backgroundImage": "bar_background",
        "foregroundElements": [
          {
            "x": 26,
            "y": 82,
            "key": "bar_foreground"
          }
        ],
        "elements": [
          {
            "x": 400,
            "y": 463,
            "key": "bar_sprites_stools"
          },
          {
            "x": 270,
            "y": 180,
            "key": "bar_sprites_drinks"
          }
        ],
        "zones": [
          {
            "key": "bar_foreground",
            "shape": "rectangle",
            "enabled": true,
            "x1": 60,
            "x2": 135,
            "y1": 100,
            "y2": 270,
            "from": -1,
            "to": -1
          }
        ]
      },
      {
        "name": "outdoor_1",
        "number": 6,
        "backgroundImage": "outdoor_1_background",
        "foregroundElements": [
          {
            "x": 308,
            "y": 148,
            "key": "outdoor_1_foreground_window"
          }
        ],
        "elements": [
          {
            "x": 400,
            "y": 454,
            "key": "outdoor_1_sprites_main"
          },
          {
            "x": 319,
            "y": 72,
            "key": "outdoor_1_sprites_window_top"
          }
        ],
        "zones": [
          {
            "key": "outdoor_1_foreground_window",
            "shape": "rectangle",
            "enabled": true,
            "x1": 308,
            "x2": 328,
            "y1": 148,
            "y2": 320,
            "from": -1,
            "to": -1
          }
        ]
      },
      {
        "name": "outdoor_2",
        "number": 7,
        "backgroundImage": "outdoor_2_background",
        "foregroundElements": [
          {
            "x": 220,
            "y": 400,
            "key" : "outdoor_2_foreground_trash"
          }
        ],
        "elements": [
          {
            "x": 400,
            "y": 301,
            "key": "outdoor_2_sprites_main"
          }
        ],
        "zones": [
          {
            "key": "outdoor_2_foreground_trash",
            "shape": "rectangle",
            "enabled": true,
            "x1": 233,
            "x2": 335,
            "y1": 420,
            "y2": 560,
            "from": -1,
            "to": -1
          }
        ]
      },
      {
        "name": "outdoor_3",
        "number": 8,
        "backgroundImage": "outdoor_3_background",
        "foregroundElements": [
          {
            "x": 452,
            "y": 148,
            "key": "outdoor_3_foreground_window"
          }
        ],
        "elements": [
          {
            "x": 400,
            "y": 464,
            "key": "outdoor_3_sprites_main"
          },
          {
            "x": 462,
            "y": 72,
            "key": "outdoor_3_sprites_window_top"
          }
        ],
        "zones": [
          {
            "key": "outdoor_3_foreground_window",
            "shape": "rectangle",
            "enabled": true,
            "x1": 452,
            "x2": 472,
            "y1": 148,
            "y2": 320,
            "from": -1,
            "to": -1
          }
        ]
      },
      {
        "name": "fish",
        "number": 9,
        "backgroundImage": "fish_background",
        "foregroundElements": [
          {
            "x": 452,
            "y": 148,
            "key": "fish_foreground_water"
          }
        ],
        "elements": [
          {
            "x": 400,
            "y": 405,
            "key": "fish_sprite_table_and_bowl"
          }
        ],
        "zones": [
          {
            "key": "fish_foreground_water",
            "shape": "circle",
            "radius": 125,
            "enabled": true,
            "x": 360,
            "y": 480,
            "from": -1,
            "to": -1
          }
        ]
      }
    ]
  }
]
